macaque/ADBKeyBoard.apk
macaque/__init__.py
macaque/__main__.py
macaque/aapt
macaque/core.py
macaque/max.widget.black
macaque/tools.py
macaque/jar/framework.jar
macaque/jar/macaque-thirdpart.jar
macaque/jar/macaque.jar
macaque/libs/arm64-v8a/libfastbot_native.so
macaque/libs/armeabi-v7a/libfastbot_native.so
macaque/libs/x86/libfastbot_native.so
macaque/libs/x86_64/libfastbot_native.so
macaque-1.0.5.dist-info/LICENSE
macaque-1.0.5.dist-info/METADATA
macaque-1.0.5.dist-info/WHEEL
macaque-1.0.5.dist-info/entry_points.txt
macaque-1.0.5.dist-info/top_level.txt
macaque-1.0.5.dist-info/RECORD
