Metadata-Version: 2.1
Name: macaque
Version: 1.0.5
Summary: Stability testing tool based on fastbot transformation.
Home-page: https://github.com/openutx
Author: lijiawei
Author-email: jiawei.li2@qq.com
License: Apache License 2.0
Keywords: utx,macaque,monkey,tools
Platform: any
Classifier: Development Status :: 5 - Production/Stable
Classifier: Environment :: Console :: Curses
Classifier: Operating System :: MacOS
Classifier: Operating System :: POSIX
Classifier: Programming Language :: Python :: 3 :: Only
Classifier: Programming Language :: Python :: 3.6
Classifier: Programming Language :: Python :: 3.7
Classifier: Programming Language :: Python :: 3.8
Classifier: Programming Language :: Python :: 3.9
Classifier: Programming Language :: Python :: Implementation :: CPython
License-File: LICENSE
Requires-Dist: airtest
Requires-Dist: fire
